[{
  "_id": {
    "$oid": "6435b9dc7709990cbb8535fd"
  },
  "question_id": 1,
  "question": "Who was your first crush ?"
},{
  "_id": {
    "$oid": "6435ba587709990cbb8535fe"
  },
  "question_id": 2,
  "question": "What is your dream in one word ?"
},{
  "_id": {
    "$oid": "6435ba937709990cbb8535ff"
  },
  "question_id": 3,
  "question": "What is your favourite destination ?"
},{
  "_id": {
    "$oid": "6435bab67709990cbb853600"
  },
  "question_id": 4,
  "question": "What is your favourite drink ?"
},{
  "_id": {
    "$oid": "6435bae47709990cbb853601"
  },
  "question_id": 5,
  "question": "Who is your inspiration ?"
}]